<?xml version="1.0" encoding="UTF-8"?>
<openerp>
 <data>
    <record id="form_sale_shop_sale_category" model="ir.ui.view">
        <field name="name">Shop</field>
        <field name="model">sale.shop</field>
        <field name="inherit_id" ref="at_sale.form_sale_shop" />
        <field name="type">form</field>
        <field name="arch" type="xml">
            <data>
                <field name="project_id" position="after">
                    <field name="sale_category_id" />
                </field>
            </data>
        </field>
    </record>
  </data>
</openerp>
